{
  "https://www.ravensburger.us/en-US/products/disney-lorcana/boosters/disney-lorcana-tcg-fabled-booster-display-box-11098639": {
    "name": "Disney Lorcana TCG: Fabled Booster Display Box",
    "stock_level": "out",
    "in_stock": false,
    "signal": "schema.org/OutOfStock",
    "last_checked": "2026-06-24T13:34:12.274344+00:00"
  },
  "https://www.ravensburger.us/en-US/products/disney-lorcana/boosters/disney-lorcana-tcg-wilds-unknownbooster-pack-display-11098887": {
    "name": "Disney Lorcana TCG: Wilds Unknown Booster Pack Display",
    "stock_level": "out",
    "in_stock": false,
    "signal": "schema.org/OutOfStock",
    "last_checked": "2026-06-24T13:34:10.979044+00:00"
  },
  "https://www.ravensburger.us/en-US/products/disney-lorcana/boosters/disney-lorcana-tcg-winterspell-booster-pack-display-24-count-11098881": {
    "name": "Disney Lorcana TCG: Winterspell Booster Pack Display - 24 Count",
    "stock_level": "out",
    "in_stock": false,
    "signal": "text:unavailable",
    "last_checked": "2026-06-24T13:34:11.539916+00:00"
  },
  "https://www.ravensburger.us/en-US/products/disney-lorcana/boosters/disney-lorcana-tcg-whispers-in-the-well-booster-display--11098812": {
    "name": "Disney Lorcana TCG: Whispers in the Well Booster Display",
    "stock_level": "out",
    "in_stock": false,
    "signal": "schema.org/OutOfStock",
    "last_checked": "2026-06-24T13:34:11.714969+00:00"
  },
  "https://www.ravensburger.us/en-US/products/disney-lorcana/boosters/disney-lorcana-tcg-reign-of-jafar-booster-display-box-24-count-11098558": {
    "name": "Disney Lorcana TCG: Reign of Jafar Booster Display Box - 24 Count",
    "stock_level": "out",
    "in_stock": false,
    "signal": "schema.org/OutOfStock",
    "last_checked": "2026-06-24T13:34:12.937629+00:00"
  },
  "https://www.ravensburger.us/en-US/products/disney-lorcana/boosters/disney-lorcana-tcg-archazias-island-booster-pack-display-11098557": {
    "name": "Disney Lorcana TCG: Archazia's Island Booster Pack Display",
    "stock_level": "out",
    "in_stock": false,
    "signal": "schema.org/OutOfStock",
    "last_checked": "2026-06-24T13:34:13.125986+00:00"
  },
  "https://www.ravensburger.us/en-US/products/disney-lorcana/boosters/disney-lorcana-tcg-azurite-sea-booster-pack-display--11098466": {
    "name": "Disney Lorcana TCG: Azurite Sea Booster Pack Display",
    "stock_level": "low",
    "in_stock": true,
    "signal": "text:only a few left",
    "last_checked": "2026-06-24T13:34:13.294233+00:00"
  },
  "https://www.ravensburger.us/en-US/products/disney-lorcana/boosters/disney-lorcana-tcg-shimmering-skies-booster-pack-display-24-count-11098455": {
    "name": "Disney Lorcana TCG: Shimmering Skies Booster Pack Display - 24 Count",
    "stock_level": "out",
    "in_stock": false,
    "signal": "schema.org/OutOfStock",
    "last_checked": "2026-06-24T13:34:14.790689+00:00"
  },
  "https://www.ravensburger.us/en-US/products/disney-lorcana/boosters/disney-lorcana-tcg-ursulas-return-booster-pack-display-11098342": {
    "name": "Disney Lorcana TCG: Ursula's Return Booster Pack Display",
    "stock_level": "out",
    "in_stock": false,
    "signal": "text:unavailable",
    "last_checked": "2026-06-24T13:34:14.980821+00:00"
  },
  "https://www.ravensburger.us/en-US/products/disney-lorcana/boosters/disney-lorcana-tcg-into-the-inklands-booster-pack-display-11098312": {
    "name": "Disney Lorcana TCG: Into the Inklands Booster Pack Display",
    "stock_level": "out",
    "in_stock": false,
    "signal": "text:unavailable",
    "last_checked": "2026-06-24T13:34:15.255681+00:00"
  },
  "https://www.ravensburger.us/en-US/products/disney-lorcana/boosters/disney-lorcana-tcg-wilds-unknownsleeved-booster-pack-11098862": {
    "name": "Disney Lorcana TCG: Wilds Unknown Sleeved Booster Pack",
    "stock_level": "out",
    "in_stock": false,
    "signal": "text:unavailable",
    "last_checked": "2026-06-24T13:34:15.445709+00:00"
  },
  "https://www.ravensburger.us/en-US/products/disney-lorcana/trove-packs/disney-lorcana-tcg-wilds-unknownillumineers-trove--11098864": {
    "name": "Disney Lorcana TCG: Wilds Unknown Illumineer's Trove",
    "stock_level": "out",
    "in_stock": false,
    "signal": "schema.org/OutOfStock",
    "last_checked": "2026-06-24T13:34:15.743383+00:00"
  },
  "https://www.ravensburger.us/en-US/products/disney-lorcana/trove-packs/winterspell-illumineers-trove-english-11098840": {
    "name": "Disney Lorcana TCG: Winterspell Illumineer's Trove",
    "stock_level": "out",
    "in_stock": false,
    "signal": "text:unavailable",
    "last_checked": "2026-06-24T13:34:15.934920+00:00"
  },
  "https://www.ravensburger.us/en-US/products/disney-lorcana/boosters/winterspell-sleeved-booster-pack-english-11098838": {
    "name": "Disney Lorcana TCG: Winterspell Sleeved Booster Pack",
    "stock_level": "out",
    "in_stock": false,
    "signal": "schema.org/OutOfStock",
    "last_checked": "2026-06-24T13:34:16.188124+00:00"
  },
  "https://www.ravensburger.us/en-US/products/disney-lorcana/starter-decks/winterspell-collection-starter-set-11090026": {
    "name": "Disney Lorcana TCG: Winterspell Collection Starter Set",
    "stock_level": "out",
    "in_stock": false,
    "signal": "schema.org/OutOfStock",
    "last_checked": "2026-06-24T13:34:18.791455+00:00"
  },
  "https://www.ravensburger.us/en-US/products/disney-lorcana/trove-packs/whispers-in-the-well-illumineers-trove-11098786": {
    "name": "Disney Lorcana TCG: Whispers in the Well Illumineer's Trove",
    "stock_level": "out",
    "in_stock": false,
    "signal": "text:unavailable",
    "last_checked": "2026-06-24T13:34:19.134910+00:00"
  },
  "https://www.ravensburger.us/en-US/products/disney-lorcana/boosters/whispers-in-the-well-sleeved-booster-packs-11098784": {
    "name": "Disney Lorcana TCG: Whispers in the Well Sleeved Booster Packs",
    "stock_level": "out",
    "in_stock": false,
    "signal": "schema.org/OutOfStock",
    "last_checked": "2026-06-24T13:34:19.477202+00:00"
  },
  "https://www.ravensburger.us/en-US/products/disney-lorcana/trove-packs/fabled-illumineers-trove-11098613": {
    "name": "Disney Lorcana TCG: Fabled Illumineer's Trove",
    "stock_level": "out",
    "in_stock": false,
    "signal": "schema.org/OutOfStock",
    "last_checked": "2026-06-24T13:34:19.634491+00:00"
  },
  "https://www.ravensburger.us/en-US/products/disney-lorcana/trove-packs/reign-of-jafar-illumineers-trove-english-11098510": {
    "name": "Disney Lorcana TCG: Reign of Jafar Illumineer's Trove",
    "stock_level": "out",
    "in_stock": false,
    "signal": "text:unavailable",
    "last_checked": "2026-06-24T13:34:19.725847+00:00"
  },
  "https://www.ravensburger.us/en-US/products/disney-lorcana/trove-packs/archazias-island-illumineers-trove-11098509": {
    "name": "Disney Lorcana TCG: Archazia's Island Illumineer's Trove",
    "stock_level": "out",
    "in_stock": false,
    "signal": "schema.org/OutOfStock",
    "last_checked": "2026-06-24T13:34:20.003863+00:00"
  },
  "https://www.ravensburger.us/en-US/products/disney-lorcana/trove-packs/azurite-sea-illumineers-trove-11098432": {
    "name": "Disney Lorcana TCG: Azurite Sea Illumineer's Trove",
    "stock_level": "out",
    "in_stock": false,
    "signal": "schema.org/OutOfStock",
    "last_checked": "2026-06-24T13:34:20.148641+00:00"
  },
  "https://www.ravensburger.us/en-US/products/disney-lorcana/boosters/shimmering-skies-sleeved-booster-packs-11098394": {
    "name": "Disney Lorcana TCG: Shimmering Skies Sleeved Booster Packs",
    "stock_level": "out",
    "in_stock": false,
    "signal": "text:unavailable",
    "last_checked": "2026-06-24T13:34:20.358366+00:00"
  },
  "https://www.ravensburger.us/en-US/products/disney-lorcana/trove-packs/-shimmering-skies-trove-11098396": {
    "name": "Disney Lorcana TCG: Shimmering Skies Illumineer's Trove",
    "stock_level": "out",
    "in_stock": false,
    "signal": "text:unavailable",
    "last_checked": "2026-06-24T13:34:20.469511+00:00"
  },
  "https://www.ravensburger.us/en-US/products/disney-lorcana/trove-packs/ursulas-return-trove-pack-11098352": {
    "name": "Disney Lorcana TCG: Ursula's Return Illumineer's Trove",
    "stock_level": "out",
    "in_stock": false,
    "signal": "text:unavailable",
    "last_checked": "2026-06-24T13:34:20.616830+00:00"
  },
  "https://www.ravensburger.us/en-US/products/disney-lorcana/boosters/ursulas-return-sleeved-booster-packs-11098350": {
    "name": "Disney Lorcana TCG: Ursula's Return Sleeved Booster Packs",
    "stock_level": "out",
    "in_stock": false,
    "signal": "schema.org/OutOfStock",
    "last_checked": "2026-06-24T13:34:20.750640+00:00"
  },
  "https://www.ravensburger.us/en-US/products/disney-lorcana/boosters/into-the-inklands-sleeved-booster-packs-11098290": {
    "name": "Disney Lorcana TCG: Into the Inklands Sleeved Booster Packs",
    "stock_level": "out",
    "in_stock": false,
    "signal": "text:unavailable",
    "last_checked": "2026-06-24T13:34:20.857562+00:00"
  },
  "https://www.ravensburger.us/en-US/products/disney-lorcana/boosters/the-first-chapter-booster-pack-11098172": {
    "name": "Disney Lorcana TCG: The First Chapter Booster Pack",
    "stock_level": "out",
    "in_stock": false,
    "signal": "schema.org/OutOfStock",
    "last_checked": "2026-06-24T13:34:21.015794+00:00"
  }
}